{
  "month": "m07",
  "flights": [
    {
      "olat": 39.87208,
      "olng": -75.24066,
      "dlat": 37.50518,
      "dlng": -77.31974,
      "meta": {
        "o": "PHL",
        "d": "RIC"
      },
      "tailNum": "30M",
      "date": "2025-07-01 00:00:00"
    },
    {
      "olat": 37.50518,
      "olng": -77.31974,
      "dlat": 36.04973,
      "dlng": -79.47301,
      "meta": {
        "o": "RIC",
        "d": "BUY"
      },
      "tailNum": "30M",
      "date": "2025-07-01 00:00:00"
    },
    {
      "olat": 36.04973,
      "olng": -79.47301,
      "dlat": 35.0,
      "dlng": -80.6,
      "meta": {
        "o": "BUY",
        "d": "EQY"
      },
      "tailNum": "30M",
      "date": "2025-07-01 00:00:00"
    },
    {
      "olat": 35.0,
      "olng": -80.6,
      "dlat": 40.65236,
      "dlng": -75.44041,
      "meta": {
        "o": "EQY",
        "d": "ABE"
      },
      "tailNum": "30M",
      "date": "2025-07-01 00:00:00"
    },
    {
      "olat": 40.65236,
      "olng": -75.44041,
      "dlat": 36.04973,
      "dlng": -79.47301,
      "meta": {
        "o": "ABE",
        "d": "BUY"
      },
      "tailNum": "30M",
      "date": "2025-07-01 00:00:00"
    },
    {
      "olat": 36.04973,
      "olng": -79.47301,
      "dlat": 39.99695,
      "dlng": -82.89216,
      "meta": {
        "o": "BUY",
        "d": "CMH"
      },
      "tailNum": "30M",
      "date": "2025-07-01 00:00:00"
    },
    {
      "olat": 39.99695,
      "olng": -82.89216,
      "dlat": 35.21375,
      "dlng": -80.94906,
      "meta": {
        "o": "CMH",
        "d": "CLT"
      },
      "tailNum": "30M",
      "date": "2025-07-01 00:00:00"
    },
    {
      "olat": 35.21375,
      "olng": -80.94906,
      "dlat": 36.04973,
      "dlng": -79.47301,
      "meta": {
        "o": "CLT",
        "d": "BUY"
      },
      "tailNum": "30M",
      "date": "2025-07-01 00:00:00"
    },
    {
      "olat": 36.04973,
      "olng": -79.47301,
      "dlat": 38.9,
      "dlng": -77.5,
      "meta": {
        "o": "BUY",
        "d": "IAD"
      },
      "tailNum": "30M",
      "date": "2025-07-02 00:00:00"
    },
    {
      "olat": 38.9,
      "olng": -77.5,
      "dlat": 36.04973,
      "dlng": -79.47301,
      "meta": {
        "o": "IAD",
        "d": "BUY"
      },
      "tailNum": "30M",
      "date": "2025-07-02 00:00:00"
    },
    {
      "olat": 36.04973,
      "olng": -79.47301,
      "dlat": 39.87208,
      "dlng": -75.24066,
      "meta": {
        "o": "BUY",
        "d": "PHL"
      },
      "tailNum": "30M",
      "date": "2025-07-05 00:00:00"
    },
    {
      "olat": 39.87208,
      "olng": -75.24066,
      "dlat": 32.89864,
      "dlng": -80.04053,
      "meta": {
        "o": "PHL",
        "d": "CHS"
      },
      "tailNum": "30M",
      "date": "2025-07-05 00:00:00"
    },
    {
      "olat": 32.89864,
      "olng": -80.04053,
      "dlat": 36.04973,
      "dlng": -79.47301,
      "meta": {
        "o": "CHS",
        "d": "BUY"
      },
      "tailNum": "30M",
      "date": "2025-07-05 00:00:00"
    },
    {
      "olat": 36.04973,
      "olng": -79.47301,
      "dlat": 38.9,
      "dlng": -77.5,
      "meta": {
        "o": "BUY",
        "d": "IAD"
      },
      "tailNum": "30M",
      "date": "2025-07-06 00:00:00"
    },
    {
      "olat": 38.9,
      "olng": -77.5,
      "dlat": 41.24167,
      "dlng": -76.92181,
      "meta": {
        "o": "IAD",
        "d": "IPT"
      },
      "tailNum": "30M",
      "date": "2025-07-06 00:00:00"
    },
    {
      "olat": 41.24167,
      "olng": -76.92181,
      "dlat": 38.9,
      "dlng": -77.5,
      "meta": {
        "o": "IPT",
        "d": "IAD"
      },
      "tailNum": "30M",
      "date": "2025-07-06 00:00:00"
    },
    {
      "olat": 38.9,
      "olng": -77.5,
      "dlat": 36.04973,
      "dlng": -79.47301,
      "meta": {
        "o": "IAD",
        "d": "BUY"
      },
      "tailNum": "30M",
      "date": "2025-07-06 00:00:00"
    },
    {
      "olat": 36.04973,
      "olng": -79.47301,
      "dlat": 37.50518,
      "dlng": -77.31974,
      "meta": {
        "o": "BUY",
        "d": "RIC"
      },
      "tailNum": "30M",
      "date": "2025-07-07 00:00:00"
    },
    {
      "olat": 37.50518,
      "olng": -77.31974,
      "dlat": 36.8946,
      "dlng": -76.20123,
      "meta": {
        "o": "RIC",
        "d": "ORF"
      },
      "tailNum": "30M",
      "date": "2025-07-07 00:00:00"
    },
    {
      "olat": 36.8946,
      "olng": -76.20123,
      "dlat": 38.17408,
      "dlng": -85.73649,
      "meta": {
        "o": "ORF",
        "d": "SDF"
      },
      "tailNum": "30M",
      "date": "2025-07-07 00:00:00"
    },
    {
      "olat": 38.17408,
      "olng": -85.73649,
      "dlat": 39.12294,
      "dlng": -94.59283,
      "meta": {
        "o": "SDF",
        "d": "MKC"
      },
      "tailNum": "30M",
      "date": "2025-07-07 00:00:00"
    },
    {
      "olat": 39.12294,
      "olng": -94.59283,
      "dlat": 36.04973,
      "dlng": -79.47301,
      "meta": {
        "o": "MKC",
        "d": "BUY"
      },
      "tailNum": "30M",
      "date": "2025-07-07 00:00:00"
    },
    {
      "olat": 36.04973,
      "olng": -79.47301,
      "dlat": 43.53293,
      "dlng": -84.07964,
      "meta": {
        "o": "BUY",
        "d": "MBS"
      },
      "tailNum": "30M",
      "date": "2025-07-15 00:00:00"
    },
    {
      "olat": 43.53293,
      "olng": -84.07964,
      "dlat": 36.04973,
      "dlng": -79.47301,
      "meta": {
        "o": "MBS",
        "d": "BUY"
      },
      "tailNum": "30M",
      "date": "2025-07-15 00:00:00"
    },
    {
      "olat": 36.04973,
      "olng": -79.47301,
      "dlat": 28.5,
      "dlng": -81.3,
      "meta": {
        "o": "BUY",
        "d": "ORL"
      },
      "tailNum": "30M",
      "date": "2025-07-16 00:00:00"
    },
    {
      "olat": 28.5,
      "olng": -81.3,
      "dlat": 30.21878,
      "dlng": -81.87717,
      "meta": {
        "o": "ORL",
        "d": "VQQ"
      },
      "tailNum": "30M",
      "date": "2025-07-16 00:00:00"
    },
    {
      "olat": 30.21878,
      "olng": -81.87717,
      "dlat": 36.04973,
      "dlng": -79.47301,
      "meta": {
        "o": "VQQ",
        "d": "BUY"
      },
      "tailNum": "30M",
      "date": "2025-07-16 00:00:00"
    },
    {
      "olat": 36.04973,
      "olng": -79.47301,
      "dlat": 35.87764,
      "dlng": -78.78747,
      "meta": {
        "o": "BUY",
        "d": "RDU"
      },
      "tailNum": "30M",
      "date": "2025-07-17 00:00:00"
    },
    {
      "olat": 35.87764,
      "olng": -78.78747,
      "dlat": 37.50518,
      "dlng": -77.31974,
      "meta": {
        "o": "RDU",
        "d": "RIC"
      },
      "tailNum": "30M",
      "date": "2025-07-17 00:00:00"
    },
    {
      "olat": 37.50518,
      "olng": -77.31974,
      "dlat": 36.04973,
      "dlng": -79.47301,
      "meta": {
        "o": "RIC",
        "d": "BUY"
      },
      "tailNum": "30M",
      "date": "2025-07-17 00:00:00"
    },
    {
      "olat": 36.04973,
      "olng": -79.47301,
      "dlat": 42.94043,
      "dlng": -78.73057,
      "meta": {
        "o": "BUY",
        "d": "BUF"
      },
      "tailNum": "30M",
      "date": "2025-07-17 00:00:00"
    },
    {
      "olat": 42.94043,
      "olng": -78.73057,
      "dlat": 35.21375,
      "dlng": -80.94906,
      "meta": {
        "o": "BUF",
        "d": "CLT"
      },
      "tailNum": "30M",
      "date": "2025-07-17 00:00:00"
    },
    {
      "olat": 35.21375,
      "olng": -80.94906,
      "dlat": 36.04973,
      "dlng": -79.47301,
      "meta": {
        "o": "CLT",
        "d": "BUY"
      },
      "tailNum": "30M",
      "date": "2025-07-17 00:00:00"
    },
    {
      "olat": 36.04973,
      "olng": -79.47301,
      "dlat": 34.89567,
      "dlng": -82.21886,
      "meta": {
        "o": "BUY",
        "d": "GSP"
      },
      "tailNum": "30M",
      "date": "2025-07-18 00:00:00"
    },
    {
      "olat": 34.89567,
      "olng": -82.21886,
      "dlat": 40.9,
      "dlng": -77.8,
      "meta": {
        "o": "GSP",
        "d": "UNV"
      },
      "tailNum": "30M",
      "date": "2025-07-18 00:00:00"
    },
    {
      "olat": 40.9,
      "olng": -77.8,
      "dlat": 36.10133,
      "dlng": -79.94112,
      "meta": {
        "o": "UNV",
        "d": "GSO"
      },
      "tailNum": "30M",
      "date": "2025-07-18 00:00:00"
    },
    {
      "olat": 36.10133,
      "olng": -79.94112,
      "dlat": 36.04973,
      "dlng": -79.47301,
      "meta": {
        "o": "GSO",
        "d": "BUY"
      },
      "tailNum": "30M",
      "date": "2025-07-27 00:00:00"
    },
    {
      "olat": 36.04973,
      "olng": -79.47301,
      "dlat": 32.89864,
      "dlng": -80.04053,
      "meta": {
        "o": "BUY",
        "d": "CHS"
      },
      "tailNum": "30M",
      "date": "2025-07-28 00:00:00"
    },
    {
      "olat": 32.89864,
      "olng": -80.04053,
      "dlat": 37.50518,
      "dlng": -77.31974,
      "meta": {
        "o": "CHS",
        "d": "RIC"
      },
      "tailNum": "30M",
      "date": "2025-07-28 00:00:00"
    },
    {
      "olat": 37.50518,
      "olng": -77.31974,
      "dlat": 36.04973,
      "dlng": -79.47301,
      "meta": {
        "o": "RIC",
        "d": "BUY"
      },
      "tailNum": "30M",
      "date": "2025-07-28 00:00:00"
    },
    {
      "olat": 36.04973,
      "olng": -79.47301,
      "dlat": 35.07285,
      "dlng": -77.04302,
      "meta": {
        "o": "BUY",
        "d": "EWN"
      },
      "tailNum": "30M",
      "date": "2025-07-29 00:00:00"
    },
    {
      "olat": 35.07285,
      "olng": -77.04302,
      "dlat": 36.04973,
      "dlng": -79.47301,
      "meta": {
        "o": "EWN",
        "d": "BUY"
      },
      "tailNum": "30M",
      "date": "2025-07-29 00:00:00"
    },
    {
      "olat": 36.04973,
      "olng": -79.47301,
      "dlat": 41.06695,
      "dlng": -73.70757,
      "meta": {
        "o": "BUY",
        "d": "HPN"
      },
      "tailNum": "30M",
      "date": "2025-07-29 00:00:00"
    },
    {
      "olat": 41.06695,
      "olng": -73.70757,
      "dlat": 36.04973,
      "dlng": -79.47301,
      "meta": {
        "o": "HPN",
        "d": "BUY"
      },
      "tailNum": "30M",
      "date": "2025-07-29 00:00:00"
    },
    {
      "olat": 36.04973,
      "olng": -79.47301,
      "dlat": 35.87764,
      "dlng": -78.78747,
      "meta": {
        "o": "BUY",
        "d": "RDU"
      },
      "tailNum": "30M",
      "date": "2025-07-29 00:00:00"
    },
    {
      "olat": 35.87764,
      "olng": -78.78747,
      "dlat": 43.90828,
      "dlng": -92.50003,
      "meta": {
        "o": "RDU",
        "d": "RST"
      },
      "tailNum": "30M",
      "date": "2025-07-30 00:00:00"
    },
    {
      "olat": 43.90828,
      "olng": -92.50003,
      "dlat": 36.10133,
      "dlng": -79.94112,
      "meta": {
        "o": "RST",
        "d": "GSO"
      },
      "tailNum": "30M",
      "date": "2025-07-30 00:00:00"
    }
  ]
}