{
  "month": "2021-10",
  "flights": [
    {
      "olat": 37.50518,
      "olng": -77.31974,
      "dlat": 36.13371,
      "dlng": -80.22199,
      "meta": {
        "o": "RIC",
        "d": "INT"
      },
      "tailNum": "94KM",
      "date": "2021-10-01 00:00:00",
      "source_file": "Flight Logs 2021.xlsx",
      "source_sheet": "94KM Baron"
    },
    {
      "olat": 36.13371,
      "olng": -80.22199,
      "dlat": 36.04973,
      "dlng": -79.47301,
      "meta": {
        "o": "INT",
        "d": "BUY"
      },
      "tailNum": "94KM",
      "date": "2021-10-01 00:00:00",
      "source_file": "Flight Logs 2021.xlsx",
      "source_sheet": "94KM Baron"
    },
    {
      "olat": 36.04973,
      "olng": -79.47301,
      "dlat": 26.2,
      "dlng": -80.2,
      "meta": {
        "o": "BUY",
        "d": "FXE"
      },
      "tailNum": "94KM",
      "date": "2021-10-04 00:00:00",
      "source_file": "Flight Logs 2021.xlsx",
      "source_sheet": "94KM Baron"
    },
    {
      "olat": 26.2,
      "olng": -80.2,
      "dlat": 28.5,
      "dlng": -81.3,
      "meta": {
        "o": "FXE",
        "d": "ORL"
      },
      "tailNum": "94KM",
      "date": "2021-10-04 00:00:00",
      "source_file": "Flight Logs 2021.xlsx",
      "source_sheet": "94KM Baron"
    },
    {
      "olat": 28.5,
      "olng": -81.3,
      "dlat": 37.50518,
      "dlng": -77.31974,
      "meta": {
        "o": "ORL",
        "d": "RIC"
      },
      "tailNum": "94KM",
      "date": "2021-10-04 00:00:00",
      "source_file": "Flight Logs 2021.xlsx",
      "source_sheet": "94KM Baron"
    },
    {
      "olat": 37.50518,
      "olng": -77.31974,
      "dlat": 36.13371,
      "dlng": -80.22199,
      "meta": {
        "o": "RIC",
        "d": "INT"
      },
      "tailNum": "94KM",
      "date": "2021-10-05 00:00:00",
      "source_file": "Flight Logs 2021.xlsx",
      "source_sheet": "94KM Baron"
    },
    {
      "olat": 36.13371,
      "olng": -80.22199,
      "dlat": 26.2,
      "dlng": -80.2,
      "meta": {
        "o": "INT",
        "d": "FXE"
      },
      "tailNum": "94KM",
      "date": "2021-10-05 00:00:00",
      "source_file": "Flight Logs 2021.xlsx",
      "source_sheet": "94KM Baron"
    },
    {
      "olat": 26.2,
      "olng": -80.2,
      "dlat": 28.5,
      "dlng": -81.3,
      "meta": {
        "o": "FXE",
        "d": "ORL"
      },
      "tailNum": "94KM",
      "date": "2021-10-05 00:00:00",
      "source_file": "Flight Logs 2021.xlsx",
      "source_sheet": "94KM Baron"
    },
    {
      "olat": 28.5,
      "olng": -81.3,
      "dlat": 37.50518,
      "dlng": -77.31974,
      "meta": {
        "o": "ORL",
        "d": "RIC"
      },
      "tailNum": "94KM",
      "date": "2021-10-05 00:00:00",
      "source_file": "Flight Logs 2021.xlsx",
      "source_sheet": "94KM Baron"
    },
    {
      "olat": 37.50518,
      "olng": -77.31974,
      "dlat": 36.04973,
      "dlng": -79.47301,
      "meta": {
        "o": "RIC",
        "d": "BUY"
      },
      "tailNum": "94KM",
      "date": "2021-10-06 00:00:00",
      "source_file": "Flight Logs 2021.xlsx",
      "source_sheet": "94KM Baron"
    },
    {
      "olat": 36.04973,
      "olng": -79.47301,
      "dlat": 36.04973,
      "dlng": -79.47301,
      "meta": {
        "o": "BUY",
        "d": "BUY"
      },
      "tailNum": "94KM",
      "date": "2021-10-06 00:00:00",
      "source_file": "Flight Logs 2021.xlsx",
      "source_sheet": "94KM Baron"
    },
    {
      "olat": 36.04973,
      "olng": -79.47301,
      "dlat": 36.04973,
      "dlng": -79.47301,
      "meta": {
        "o": "BUY",
        "d": "BUY"
      },
      "tailNum": "94KM",
      "date": "2021-10-06 00:00:00",
      "source_file": "Flight Logs 2021.xlsx",
      "source_sheet": "94KM Baron"
    },
    {
      "olat": 36.04973,
      "olng": -79.47301,
      "dlat": 26.2,
      "dlng": -80.2,
      "meta": {
        "o": "BUY",
        "d": "FXE"
      },
      "tailNum": "94KM",
      "date": "2021-10-06 00:00:00",
      "source_file": "Flight Logs 2021.xlsx",
      "source_sheet": "94KM Baron"
    },
    {
      "olat": 26.2,
      "olng": -80.2,
      "dlat": 28.5,
      "dlng": -81.3,
      "meta": {
        "o": "FXE",
        "d": "ORL"
      },
      "tailNum": "94KM",
      "date": "2021-10-06 00:00:00",
      "source_file": "Flight Logs 2021.xlsx",
      "source_sheet": "94KM Baron"
    },
    {
      "olat": 28.5,
      "olng": -81.3,
      "dlat": 37.50518,
      "dlng": -77.31974,
      "meta": {
        "o": "ORL",
        "d": "RIC"
      },
      "tailNum": "94KM",
      "date": "2021-10-06 00:00:00",
      "source_file": "Flight Logs 2021.xlsx",
      "source_sheet": "94KM Baron"
    },
    {
      "olat": 37.50518,
      "olng": -77.31974,
      "dlat": 36.04973,
      "dlng": -79.47301,
      "meta": {
        "o": "RIC",
        "d": "BUY"
      },
      "tailNum": "94KM",
      "date": "2021-10-07 00:00:00",
      "source_file": "Flight Logs 2021.xlsx",
      "source_sheet": "94KM Baron"
    },
    {
      "olat": 36.04973,
      "olng": -79.47301,
      "dlat": 35.6,
      "dlng": -79.1,
      "meta": {
        "o": "BUY",
        "d": "TTA"
      },
      "tailNum": "94KM",
      "date": "2021-10-07 00:00:00",
      "source_file": "Flight Logs 2021.xlsx",
      "source_sheet": "94KM Baron"
    },
    {
      "olat": 35.6,
      "olng": -79.1,
      "dlat": 38.39811,
      "dlng": -77.45547,
      "meta": {
        "o": "TTA",
        "d": "RMN"
      },
      "tailNum": "94KM",
      "date": "2021-10-07 00:00:00",
      "source_file": "Flight Logs 2021.xlsx",
      "source_sheet": "94KM Baron"
    },
    {
      "olat": 38.39811,
      "olng": -77.45547,
      "dlat": 35.6,
      "dlng": -79.1,
      "meta": {
        "o": "RMN",
        "d": "TTA"
      },
      "tailNum": "94KM",
      "date": "2021-10-07 00:00:00",
      "source_file": "Flight Logs 2021.xlsx",
      "source_sheet": "94KM Baron"
    },
    {
      "olat": 35.6,
      "olng": -79.1,
      "dlat": 36.04973,
      "dlng": -79.47301,
      "meta": {
        "o": "TTA",
        "d": "BUY"
      },
      "tailNum": "94KM",
      "date": "2021-10-07 00:00:00",
      "source_file": "Flight Logs 2021.xlsx",
      "source_sheet": "94KM Baron"
    },
    {
      "olat": 36.04973,
      "olng": -79.47301,
      "dlat": 26.2,
      "dlng": -80.2,
      "meta": {
        "o": "BUY",
        "d": "FXE"
      },
      "tailNum": "94KM",
      "date": "2021-10-07 00:00:00",
      "source_file": "Flight Logs 2021.xlsx",
      "source_sheet": "94KM Baron"
    },
    {
      "olat": 26.2,
      "olng": -80.2,
      "dlat": 28.5,
      "dlng": -81.3,
      "meta": {
        "o": "FXE",
        "d": "ORL"
      },
      "tailNum": "94KM",
      "date": "2021-10-07 00:00:00",
      "source_file": "Flight Logs 2021.xlsx",
      "source_sheet": "94KM Baron"
    },
    {
      "olat": 28.5,
      "olng": -81.3,
      "dlat": 37.50518,
      "dlng": -77.31974,
      "meta": {
        "o": "ORL",
        "d": "RIC"
      },
      "tailNum": "94KM",
      "date": "2021-10-07 00:00:00",
      "source_file": "Flight Logs 2021.xlsx",
      "source_sheet": "94KM Baron"
    },
    {
      "olat": 37.50518,
      "olng": -77.31974,
      "dlat": 36.04973,
      "dlng": -79.47301,
      "meta": {
        "o": "RIC",
        "d": "BUY"
      },
      "tailNum": "94KM",
      "date": "2021-10-08 00:00:00",
      "source_file": "Flight Logs 2021.xlsx",
      "source_sheet": "94KM Baron"
    },
    {
      "olat": 36.04973,
      "olng": -79.47301,
      "dlat": 26.2,
      "dlng": -80.2,
      "meta": {
        "o": "BUY",
        "d": "FXE"
      },
      "tailNum": "94KM",
      "date": "2021-10-08 00:00:00",
      "source_file": "Flight Logs 2021.xlsx",
      "source_sheet": "94KM Baron"
    },
    {
      "olat": 26.2,
      "olng": -80.2,
      "dlat": 28.5,
      "dlng": -81.3,
      "meta": {
        "o": "FXE",
        "d": "ORL"
      },
      "tailNum": "94KM",
      "date": "2021-10-08 00:00:00",
      "source_file": "Flight Logs 2021.xlsx",
      "source_sheet": "94KM Baron"
    },
    {
      "olat": 28.5,
      "olng": -81.3,
      "dlat": 37.50518,
      "dlng": -77.31974,
      "meta": {
        "o": "ORL",
        "d": "RIC"
      },
      "tailNum": "94KM",
      "date": "2021-10-08 00:00:00",
      "source_file": "Flight Logs 2021.xlsx",
      "source_sheet": "94KM Baron"
    },
    {
      "olat": 37.50518,
      "olng": -77.31974,
      "dlat": 36.04973,
      "dlng": -79.47301,
      "meta": {
        "o": "RIC",
        "d": "BUY"
      },
      "tailNum": "94KM",
      "date": "2021-10-09 00:00:00",
      "source_file": "Flight Logs 2021.xlsx",
      "source_sheet": "94KM Baron"
    },
    {
      "olat": 36.04973,
      "olng": -79.47301,
      "dlat": 36.04973,
      "dlng": -79.47301,
      "meta": {
        "o": "BUY",
        "d": "BUY"
      },
      "tailNum": "94KM",
      "date": "2021-10-10 00:00:00",
      "source_file": "Flight Logs 2021.xlsx",
      "source_sheet": "94KM Baron"
    },
    {
      "olat": 36.04973,
      "olng": -79.47301,
      "dlat": 36.13371,
      "dlng": -80.22199,
      "meta": {
        "o": "BUY",
        "d": "INT"
      },
      "tailNum": "94KM",
      "date": "2021-10-11 00:00:00",
      "source_file": "Flight Logs 2021.xlsx",
      "source_sheet": "94KM Baron"
    },
    {
      "olat": 36.13371,
      "olng": -80.22199,
      "dlat": 36.13371,
      "dlng": -80.22199,
      "meta": {
        "o": "INT",
        "d": "INT"
      },
      "tailNum": "94KM",
      "date": "2021-10-11 00:00:00",
      "source_file": "Flight Logs 2021.xlsx",
      "source_sheet": "94KM Baron"
    },
    {
      "olat": 36.13371,
      "olng": -80.22199,
      "dlat": 36.04973,
      "dlng": -79.47301,
      "meta": {
        "o": "INT",
        "d": "BUY"
      },
      "tailNum": "94KM",
      "date": "2021-10-11 00:00:00",
      "source_file": "Flight Logs 2021.xlsx",
      "source_sheet": "94KM Baron"
    },
    {
      "olat": 36.04973,
      "olng": -79.47301,
      "dlat": 36.13371,
      "dlng": -80.22199,
      "meta": {
        "o": "BUY",
        "d": "INT"
      },
      "tailNum": "94KM",
      "date": "2021-10-11 00:00:00",
      "source_file": "Flight Logs 2021.xlsx",
      "source_sheet": "94KM Baron"
    },
    {
      "olat": 36.13371,
      "olng": -80.22199,
      "dlat": 26.2,
      "dlng": -80.2,
      "meta": {
        "o": "INT",
        "d": "FXE"
      },
      "tailNum": "94KM",
      "date": "2021-10-12 00:00:00",
      "source_file": "Flight Logs 2021.xlsx",
      "source_sheet": "94KM Baron"
    },
    {
      "olat": 26.2,
      "olng": -80.2,
      "dlat": 28.5,
      "dlng": -81.3,
      "meta": {
        "o": "FXE",
        "d": "ORL"
      },
      "tailNum": "94KM",
      "date": "2021-10-12 00:00:00",
      "source_file": "Flight Logs 2021.xlsx",
      "source_sheet": "94KM Baron"
    },
    {
      "olat": 28.5,
      "olng": -81.3,
      "dlat": 37.50518,
      "dlng": -77.31974,
      "meta": {
        "o": "ORL",
        "d": "RIC"
      },
      "tailNum": "94KM",
      "date": "2021-10-12 00:00:00",
      "source_file": "Flight Logs 2021.xlsx",
      "source_sheet": "94KM Baron"
    },
    {
      "olat": 37.50518,
      "olng": -77.31974,
      "dlat": 36.13371,
      "dlng": -80.22199,
      "meta": {
        "o": "RIC",
        "d": "INT"
      },
      "tailNum": "94KM",
      "date": "2021-10-13 00:00:00",
      "source_file": "Flight Logs 2021.xlsx",
      "source_sheet": "94KM Baron"
    },
    {
      "olat": 36.13371,
      "olng": -80.22199,
      "dlat": 36.10133,
      "dlng": -79.94112,
      "meta": {
        "o": "INT",
        "d": "GSO"
      },
      "tailNum": "94KM",
      "date": "2021-10-13 00:00:00",
      "source_file": "Flight Logs 2021.xlsx",
      "source_sheet": "94KM Baron"
    },
    {
      "olat": 36.10133,
      "olng": -79.94112,
      "dlat": 32.921,
      "dlng": -80.64061,
      "meta": {
        "o": "GSO",
        "d": "RBW"
      },
      "tailNum": "94KM",
      "date": "2021-10-13 00:00:00",
      "source_file": "Flight Logs 2021.xlsx",
      "source_sheet": "94KM Baron"
    },
    {
      "olat": 32.921,
      "olng": -80.64061,
      "dlat": 36.04973,
      "dlng": -79.47301,
      "meta": {
        "o": "RBW",
        "d": "BUY"
      },
      "tailNum": "94KM",
      "date": "2021-10-13 00:00:00",
      "source_file": "Flight Logs 2021.xlsx",
      "source_sheet": "94KM Baron"
    },
    {
      "olat": 36.04973,
      "olng": -79.47301,
      "dlat": 26.2,
      "dlng": -80.2,
      "meta": {
        "o": "BUY",
        "d": "FXE"
      },
      "tailNum": "94KM",
      "date": "2021-10-13 00:00:00",
      "source_file": "Flight Logs 2021.xlsx",
      "source_sheet": "94KM Baron"
    },
    {
      "olat": 26.2,
      "olng": -80.2,
      "dlat": 28.5,
      "dlng": -81.3,
      "meta": {
        "o": "FXE",
        "d": "ORL"
      },
      "tailNum": "94KM",
      "date": "2021-10-13 00:00:00",
      "source_file": "Flight Logs 2021.xlsx",
      "source_sheet": "94KM Baron"
    },
    {
      "olat": 28.5,
      "olng": -81.3,
      "dlat": 37.50518,
      "dlng": -77.31974,
      "meta": {
        "o": "ORL",
        "d": "RIC"
      },
      "tailNum": "94KM",
      "date": "2021-10-13 00:00:00",
      "source_file": "Flight Logs 2021.xlsx",
      "source_sheet": "94KM Baron"
    },
    {
      "olat": 37.50518,
      "olng": -77.31974,
      "dlat": 36.04973,
      "dlng": -79.47301,
      "meta": {
        "o": "RIC",
        "d": "BUY"
      },
      "tailNum": "94KM",
      "date": "2021-10-14 00:00:00",
      "source_file": "Flight Logs 2021.xlsx",
      "source_sheet": "94KM Baron"
    },
    {
      "olat": 36.04973,
      "olng": -79.47301,
      "dlat": 26.2,
      "dlng": -80.2,
      "meta": {
        "o": "BUY",
        "d": "FXE"
      },
      "tailNum": "94KM",
      "date": "2021-10-14 00:00:00",
      "source_file": "Flight Logs 2021.xlsx",
      "source_sheet": "94KM Baron"
    },
    {
      "olat": 26.2,
      "olng": -80.2,
      "dlat": 28.5,
      "dlng": -81.3,
      "meta": {
        "o": "FXE",
        "d": "ORL"
      },
      "tailNum": "94KM",
      "date": "2021-10-14 00:00:00",
      "source_file": "Flight Logs 2021.xlsx",
      "source_sheet": "94KM Baron"
    },
    {
      "olat": 28.5,
      "olng": -81.3,
      "dlat": 37.50518,
      "dlng": -77.31974,
      "meta": {
        "o": "ORL",
        "d": "RIC"
      },
      "tailNum": "94KM",
      "date": "2021-10-14 00:00:00",
      "source_file": "Flight Logs 2021.xlsx",
      "source_sheet": "94KM Baron"
    },
    {
      "olat": 37.50518,
      "olng": -77.31974,
      "dlat": 36.04973,
      "dlng": -79.47301,
      "meta": {
        "o": "RIC",
        "d": "BUY"
      },
      "tailNum": "94KM",
      "date": "2021-10-15 00:00:00",
      "source_file": "Flight Logs 2021.xlsx",
      "source_sheet": "94KM Baron"
    },
    {
      "olat": 36.04973,
      "olng": -79.47301,
      "dlat": 38.9,
      "dlng": -77.5,
      "meta": {
        "o": "BUY",
        "d": "IAD"
      },
      "tailNum": "94KM",
      "date": "2021-10-15 00:00:00",
      "source_file": "Flight Logs 2021.xlsx",
      "source_sheet": "94KM Baron"
    },
    {
      "olat": 38.9,
      "olng": -77.5,
      "dlat": 36.04973,
      "dlng": -79.47301,
      "meta": {
        "o": "IAD",
        "d": "BUY"
      },
      "tailNum": "94KM",
      "date": "2021-10-15 00:00:00",
      "source_file": "Flight Logs 2021.xlsx",
      "source_sheet": "94KM Baron"
    },
    {
      "olat": 36.04973,
      "olng": -79.47301,
      "dlat": 26.2,
      "dlng": -80.2,
      "meta": {
        "o": "BUY",
        "d": "FXE"
      },
      "tailNum": "94KM",
      "date": "2021-10-15 00:00:00",
      "source_file": "Flight Logs 2021.xlsx",
      "source_sheet": "94KM Baron"
    },
    {
      "olat": 26.2,
      "olng": -80.2,
      "dlat": 28.5,
      "dlng": -81.3,
      "meta": {
        "o": "FXE",
        "d": "ORL"
      },
      "tailNum": "94KM",
      "date": "2021-10-15 00:00:00",
      "source_file": "Flight Logs 2021.xlsx",
      "source_sheet": "94KM Baron"
    },
    {
      "olat": 28.5,
      "olng": -81.3,
      "dlat": 37.50518,
      "dlng": -77.31974,
      "meta": {
        "o": "ORL",
        "d": "RIC"
      },
      "tailNum": "94KM",
      "date": "2021-10-15 00:00:00",
      "source_file": "Flight Logs 2021.xlsx",
      "source_sheet": "94KM Baron"
    },
    {
      "olat": 37.50518,
      "olng": -77.31974,
      "dlat": 36.04973,
      "dlng": -79.47301,
      "meta": {
        "o": "RIC",
        "d": "BUY"
      },
      "tailNum": "94KM",
      "date": "2021-10-16 00:00:00",
      "source_file": "Flight Logs 2021.xlsx",
      "source_sheet": "94KM Baron"
    },
    {
      "olat": 36.04973,
      "olng": -79.47301,
      "dlat": 26.2,
      "dlng": -80.2,
      "meta": {
        "o": "BUY",
        "d": "FXE"
      },
      "tailNum": "94KM",
      "date": "2021-10-16 00:00:00",
      "source_file": "Flight Logs 2021.xlsx",
      "source_sheet": "94KM Baron"
    },
    {
      "olat": 26.2,
      "olng": -80.2,
      "dlat": 28.5,
      "dlng": -81.3,
      "meta": {
        "o": "FXE",
        "d": "ORL"
      },
      "tailNum": "94KM",
      "date": "2021-10-16 00:00:00",
      "source_file": "Flight Logs 2021.xlsx",
      "source_sheet": "94KM Baron"
    },
    {
      "olat": 28.5,
      "olng": -81.3,
      "dlat": 37.50518,
      "dlng": -77.31974,
      "meta": {
        "o": "ORL",
        "d": "RIC"
      },
      "tailNum": "94KM",
      "date": "2021-10-16 00:00:00",
      "source_file": "Flight Logs 2021.xlsx",
      "source_sheet": "94KM Baron"
    },
    {
      "olat": 37.50518,
      "olng": -77.31974,
      "dlat": 36.04973,
      "dlng": -79.47301,
      "meta": {
        "o": "RIC",
        "d": "BUY"
      },
      "tailNum": "94KM",
      "date": "2021-10-17 00:00:00",
      "source_file": "Flight Logs 2021.xlsx",
      "source_sheet": "94KM Baron"
    },
    {
      "olat": 36.04973,
      "olng": -79.47301,
      "dlat": 32.921,
      "dlng": -80.64061,
      "meta": {
        "o": "BUY",
        "d": "RBW"
      },
      "tailNum": "94KM",
      "date": "2021-10-17 00:00:00",
      "source_file": "Flight Logs 2021.xlsx",
      "source_sheet": "94KM Baron"
    },
    {
      "olat": 32.921,
      "olng": -80.64061,
      "dlat": 36.10133,
      "dlng": -79.94112,
      "meta": {
        "o": "RBW",
        "d": "GSO"
      },
      "tailNum": "94KM",
      "date": "2021-10-17 00:00:00",
      "source_file": "Flight Logs 2021.xlsx",
      "source_sheet": "94KM Baron"
    },
    {
      "olat": 36.10133,
      "olng": -79.94112,
      "dlat": 36.04973,
      "dlng": -79.47301,
      "meta": {
        "o": "GSO",
        "d": "BUY"
      },
      "tailNum": "94KM",
      "date": "2021-10-17 00:00:00",
      "source_file": "Flight Logs 2021.xlsx",
      "source_sheet": "94KM Baron"
    },
    {
      "olat": 36.04973,
      "olng": -79.47301,
      "dlat": 36.13371,
      "dlng": -80.22199,
      "meta": {
        "o": "BUY",
        "d": "INT"
      },
      "tailNum": "94KM",
      "date": "2021-10-17 00:00:00",
      "source_file": "Flight Logs 2021.xlsx",
      "source_sheet": "94KM Baron"
    },
    {
      "olat": 36.13371,
      "olng": -80.22199,
      "dlat": 26.2,
      "dlng": -80.2,
      "meta": {
        "o": "INT",
        "d": "FXE"
      },
      "tailNum": "94KM",
      "date": "2021-10-21 00:00:00",
      "source_file": "Flight Logs 2021.xlsx",
      "source_sheet": "94KM Baron"
    },
    {
      "olat": 26.2,
      "olng": -80.2,
      "dlat": 28.5,
      "dlng": -81.3,
      "meta": {
        "o": "FXE",
        "d": "ORL"
      },
      "tailNum": "94KM",
      "date": "2021-10-21 00:00:00",
      "source_file": "Flight Logs 2021.xlsx",
      "source_sheet": "94KM Baron"
    },
    {
      "olat": 28.5,
      "olng": -81.3,
      "dlat": 37.50518,
      "dlng": -77.31974,
      "meta": {
        "o": "ORL",
        "d": "RIC"
      },
      "tailNum": "94KM",
      "date": "2021-10-21 00:00:00",
      "source_file": "Flight Logs 2021.xlsx",
      "source_sheet": "94KM Baron"
    },
    {
      "olat": 37.50518,
      "olng": -77.31974,
      "dlat": 36.04973,
      "dlng": -79.47301,
      "meta": {
        "o": "RIC",
        "d": "BUY"
      },
      "tailNum": "94KM",
      "date": "2021-10-22 00:00:00",
      "source_file": "Flight Logs 2021.xlsx",
      "source_sheet": "94KM Baron"
    },
    {
      "olat": 36.04973,
      "olng": -79.47301,
      "dlat": 26.2,
      "dlng": -80.2,
      "meta": {
        "o": "BUY",
        "d": "FXE"
      },
      "tailNum": "94KM",
      "date": "2021-10-22 00:00:00",
      "source_file": "Flight Logs 2021.xlsx",
      "source_sheet": "94KM Baron"
    },
    {
      "olat": 26.2,
      "olng": -80.2,
      "dlat": 28.5,
      "dlng": -81.3,
      "meta": {
        "o": "FXE",
        "d": "ORL"
      },
      "tailNum": "94KM",
      "date": "2021-10-22 00:00:00",
      "source_file": "Flight Logs 2021.xlsx",
      "source_sheet": "94KM Baron"
    },
    {
      "olat": 28.5,
      "olng": -81.3,
      "dlat": 37.50518,
      "dlng": -77.31974,
      "meta": {
        "o": "ORL",
        "d": "RIC"
      },
      "tailNum": "94KM",
      "date": "2021-10-22 00:00:00",
      "source_file": "Flight Logs 2021.xlsx",
      "source_sheet": "94KM Baron"
    },
    {
      "olat": 37.50518,
      "olng": -77.31974,
      "dlat": 36.04973,
      "dlng": -79.47301,
      "meta": {
        "o": "RIC",
        "d": "BUY"
      },
      "tailNum": "94KM",
      "date": "2021-10-23 00:00:00",
      "source_file": "Flight Logs 2021.xlsx",
      "source_sheet": "94KM Baron"
    },
    {
      "olat": 36.04973,
      "olng": -79.47301,
      "dlat": 26.2,
      "dlng": -80.2,
      "meta": {
        "o": "BUY",
        "d": "FXE"
      },
      "tailNum": "94KM",
      "date": "2021-10-23 00:00:00",
      "source_file": "Flight Logs 2021.xlsx",
      "source_sheet": "94KM Baron"
    },
    {
      "olat": 26.2,
      "olng": -80.2,
      "dlat": 28.5,
      "dlng": -81.3,
      "meta": {
        "o": "FXE",
        "d": "ORL"
      },
      "tailNum": "94KM",
      "date": "2021-10-23 00:00:00",
      "source_file": "Flight Logs 2021.xlsx",
      "source_sheet": "94KM Baron"
    },
    {
      "olat": 28.5,
      "olng": -81.3,
      "dlat": 37.50518,
      "dlng": -77.31974,
      "meta": {
        "o": "ORL",
        "d": "RIC"
      },
      "tailNum": "94KM",
      "date": "2021-10-23 00:00:00",
      "source_file": "Flight Logs 2021.xlsx",
      "source_sheet": "94KM Baron"
    },
    {
      "olat": 37.50518,
      "olng": -77.31974,
      "dlat": 36.04973,
      "dlng": -79.47301,
      "meta": {
        "o": "RIC",
        "d": "BUY"
      },
      "tailNum": "94KM",
      "date": "2021-10-24 00:00:00",
      "source_file": "Flight Logs 2021.xlsx",
      "source_sheet": "94KM Baron"
    },
    {
      "olat": 36.04973,
      "olng": -79.47301,
      "dlat": 26.2,
      "dlng": -80.2,
      "meta": {
        "o": "BUY",
        "d": "FXE"
      },
      "tailNum": "94KM",
      "date": "2021-10-24 00:00:00",
      "source_file": "Flight Logs 2021.xlsx",
      "source_sheet": "94KM Baron"
    },
    {
      "olat": 26.2,
      "olng": -80.2,
      "dlat": 28.5,
      "dlng": -81.3,
      "meta": {
        "o": "FXE",
        "d": "ORL"
      },
      "tailNum": "94KM",
      "date": "2021-10-24 00:00:00",
      "source_file": "Flight Logs 2021.xlsx",
      "source_sheet": "94KM Baron"
    },
    {
      "olat": 28.5,
      "olng": -81.3,
      "dlat": 37.50518,
      "dlng": -77.31974,
      "meta": {
        "o": "ORL",
        "d": "RIC"
      },
      "tailNum": "94KM",
      "date": "2021-10-24 00:00:00",
      "source_file": "Flight Logs 2021.xlsx",
      "source_sheet": "94KM Baron"
    },
    {
      "olat": 37.50518,
      "olng": -77.31974,
      "dlat": 36.04973,
      "dlng": -79.47301,
      "meta": {
        "o": "RIC",
        "d": "BUY"
      },
      "tailNum": "94KM",
      "date": "2021-10-25 00:00:00",
      "source_file": "Flight Logs 2021.xlsx",
      "source_sheet": "94KM Baron"
    },
    {
      "olat": 36.04973,
      "olng": -79.47301,
      "dlat": 36.10133,
      "dlng": -79.94112,
      "meta": {
        "o": "BUY",
        "d": "GSO"
      },
      "tailNum": "94KM",
      "date": "2021-10-27 00:00:00",
      "source_file": "Flight Logs 2021.xlsx",
      "source_sheet": "94KM Baron"
    },
    {
      "olat": 36.10133,
      "olng": -79.94112,
      "dlat": 36.10133,
      "dlng": -79.94112,
      "meta": {
        "o": "GSO",
        "d": "GSO"
      },
      "tailNum": "94KM",
      "date": "2021-10-27 00:00:00",
      "source_file": "Flight Logs 2021.xlsx",
      "source_sheet": "94KM Baron"
    },
    {
      "olat": 36.10133,
      "olng": -79.94112,
      "dlat": 36.04973,
      "dlng": -79.47301,
      "meta": {
        "o": "GSO",
        "d": "BUY"
      },
      "tailNum": "94KM",
      "date": "2021-10-27 00:00:00",
      "source_file": "Flight Logs 2021.xlsx",
      "source_sheet": "94KM Baron"
    },
    {
      "olat": 36.04973,
      "olng": -79.47301,
      "dlat": 36.04973,
      "dlng": -79.47301,
      "meta": {
        "o": "BUY",
        "d": "BUY"
      },
      "tailNum": "94KM",
      "date": "2021-10-27 00:00:00",
      "source_file": "Flight Logs 2021.xlsx",
      "source_sheet": "94KM Baron"
    },
    {
      "olat": 36.04973,
      "olng": -79.47301,
      "dlat": 36.04973,
      "dlng": -79.47301,
      "meta": {
        "o": "BUY",
        "d": "BUY"
      },
      "tailNum": "94KM",
      "date": "2021-10-27 00:00:00",
      "source_file": "Flight Logs 2021.xlsx",
      "source_sheet": "94KM Baron"
    },
    {
      "olat": 36.04973,
      "olng": -79.47301,
      "dlat": 36.13371,
      "dlng": -80.22199,
      "meta": {
        "o": "BUY",
        "d": "INT"
      },
      "tailNum": "94KM",
      "date": "2021-10-27 00:00:00",
      "source_file": "Flight Logs 2021.xlsx",
      "source_sheet": "94KM Baron"
    },
    {
      "olat": 36.13371,
      "olng": -80.22199,
      "dlat": 26.2,
      "dlng": -80.2,
      "meta": {
        "o": "INT",
        "d": "FXE"
      },
      "tailNum": "94KM",
      "date": "2021-10-28 00:00:00",
      "source_file": "Flight Logs 2021.xlsx",
      "source_sheet": "94KM Baron"
    },
    {
      "olat": 26.2,
      "olng": -80.2,
      "dlat": 28.5,
      "dlng": -81.3,
      "meta": {
        "o": "FXE",
        "d": "ORL"
      },
      "tailNum": "94KM",
      "date": "2021-10-28 00:00:00",
      "source_file": "Flight Logs 2021.xlsx",
      "source_sheet": "94KM Baron"
    },
    {
      "olat": 28.5,
      "olng": -81.3,
      "dlat": 37.50518,
      "dlng": -77.31974,
      "meta": {
        "o": "ORL",
        "d": "RIC"
      },
      "tailNum": "94KM",
      "date": "2021-10-28 00:00:00",
      "source_file": "Flight Logs 2021.xlsx",
      "source_sheet": "94KM Baron"
    },
    {
      "olat": 37.50518,
      "olng": -77.31974,
      "dlat": 36.13371,
      "dlng": -80.22199,
      "meta": {
        "o": "RIC",
        "d": "INT"
      },
      "tailNum": "94KM",
      "date": "2021-10-29 00:00:00",
      "source_file": "Flight Logs 2021.xlsx",
      "source_sheet": "94KM Baron"
    },
    {
      "olat": 36.13371,
      "olng": -80.22199,
      "dlat": 26.2,
      "dlng": -80.2,
      "meta": {
        "o": "INT",
        "d": "FXE"
      },
      "tailNum": "94KM",
      "date": "2021-10-29 00:00:00",
      "source_file": "Flight Logs 2021.xlsx",
      "source_sheet": "94KM Baron"
    },
    {
      "olat": 26.2,
      "olng": -80.2,
      "dlat": 28.5,
      "dlng": -81.3,
      "meta": {
        "o": "FXE",
        "d": "ORL"
      },
      "tailNum": "94KM",
      "date": "2021-10-29 00:00:00",
      "source_file": "Flight Logs 2021.xlsx",
      "source_sheet": "94KM Baron"
    },
    {
      "olat": 28.5,
      "olng": -81.3,
      "dlat": 37.50518,
      "dlng": -77.31974,
      "meta": {
        "o": "ORL",
        "d": "RIC"
      },
      "tailNum": "94KM",
      "date": "2021-10-29 00:00:00",
      "source_file": "Flight Logs 2021.xlsx",
      "source_sheet": "94KM Baron"
    },
    {
      "olat": 37.50518,
      "olng": -77.31974,
      "dlat": 36.04973,
      "dlng": -79.47301,
      "meta": {
        "o": "RIC",
        "d": "BUY"
      },
      "tailNum": "94KM",
      "date": "2021-10-30 00:00:00",
      "source_file": "Flight Logs 2021.xlsx",
      "source_sheet": "94KM Baron"
    },
    {
      "olat": 36.04973,
      "olng": -79.47301,
      "dlat": 26.2,
      "dlng": -80.2,
      "meta": {
        "o": "BUY",
        "d": "FXE"
      },
      "tailNum": "94KM",
      "date": "2021-10-30 00:00:00",
      "source_file": "Flight Logs 2021.xlsx",
      "source_sheet": "94KM Baron"
    },
    {
      "olat": 26.2,
      "olng": -80.2,
      "dlat": 28.5,
      "dlng": -81.3,
      "meta": {
        "o": "FXE",
        "d": "ORL"
      },
      "tailNum": "94KM",
      "date": "2021-10-30 00:00:00",
      "source_file": "Flight Logs 2021.xlsx",
      "source_sheet": "94KM Baron"
    },
    {
      "olat": 28.5,
      "olng": -81.3,
      "dlat": 37.50518,
      "dlng": -77.31974,
      "meta": {
        "o": "ORL",
        "d": "RIC"
      },
      "tailNum": "94KM",
      "date": "2021-10-30 00:00:00",
      "source_file": "Flight Logs 2021.xlsx",
      "source_sheet": "94KM Baron"
    },
    {
      "olat": 37.50518,
      "olng": -77.31974,
      "dlat": 36.04973,
      "dlng": -79.47301,
      "meta": {
        "o": "RIC",
        "d": "BUY"
      },
      "tailNum": "94KM",
      "date": "2021-10-31 00:00:00",
      "source_file": "Flight Logs 2021.xlsx",
      "source_sheet": "94KM Baron"
    },
    {
      "olat": 36.04973,
      "olng": -79.47301,
      "dlat": 36.04973,
      "dlng": -79.47301,
      "meta": {
        "o": "BUY",
        "d": "BUY"
      },
      "tailNum": "94KM",
      "date": "2021-10-31 00:00:00",
      "source_file": "Flight Logs 2021.xlsx",
      "source_sheet": "94KM Baron"
    },
    {
      "olat": 36.04973,
      "olng": -79.47301,
      "dlat": 34.82917,
      "dlng": -77.61214,
      "meta": {
        "o": "BUY",
        "d": "OAJ"
      },
      "tailNum": "94KM",
      "date": "2021-10-31 00:00:00",
      "source_file": "Flight Logs 2021.xlsx",
      "source_sheet": "94KM Baron"
    },
    {
      "olat": 34.82917,
      "olng": -77.61214,
      "dlat": 36.04973,
      "dlng": -79.47301,
      "meta": {
        "o": "OAJ",
        "d": "BUY"
      },
      "tailNum": "94KM",
      "date": "2021-10-31 00:00:00",
      "source_file": "Flight Logs 2021.xlsx",
      "source_sheet": "94KM Baron"
    },
    {
      "olat": 36.04973,
      "olng": -79.47301,
      "dlat": 26.2,
      "dlng": -80.2,
      "meta": {
        "o": "BUY",
        "d": "FXE"
      },
      "tailNum": "94KM",
      "date": "2021-10-31 00:00:00",
      "source_file": "Flight Logs 2021.xlsx",
      "source_sheet": "94KM Baron"
    },
    {
      "olat": 26.2,
      "olng": -80.2,
      "dlat": 28.5,
      "dlng": -81.3,
      "meta": {
        "o": "FXE",
        "d": "ORL"
      },
      "tailNum": "94KM",
      "date": "2021-10-31 00:00:00",
      "source_file": "Flight Logs 2021.xlsx",
      "source_sheet": "94KM Baron"
    },
    {
      "olat": 28.5,
      "olng": -81.3,
      "dlat": 37.50518,
      "dlng": -77.31974,
      "meta": {
        "o": "ORL",
        "d": "RIC"
      },
      "tailNum": "94KM",
      "date": "2021-10-31 00:00:00",
      "source_file": "Flight Logs 2021.xlsx",
      "source_sheet": "94KM Baron"
    },
    {
      "olat": 39.57012,
      "olng": -104.84929,
      "dlat": 36.04973,
      "dlng": -79.47301,
      "meta": {
        "o": "APA",
        "d": "BUY"
      },
      "tailNum": "",
      "date": "2021-10-01 00:00:00",
      "source_file": "Flight Logs 2021.xlsx",
      "source_sheet": "242ML CJ"
    },
    {
      "olat": 36.04973,
      "olng": -79.47301,
      "dlat": 38.79061,
      "dlng": -97.65222,
      "meta": {
        "o": "BUY",
        "d": "SLN"
      },
      "tailNum": "",
      "date": "2021-10-01 00:00:00",
      "source_file": "Flight Logs 2021.xlsx",
      "source_sheet": "242ML CJ"
    },
    {
      "olat": 38.79061,
      "olng": -97.65222,
      "dlat": 39.57012,
      "dlng": -104.84929,
      "meta": {
        "o": "SLN",
        "d": "APA"
      },
      "tailNum": "",
      "date": "2021-10-01 00:00:00",
      "source_file": "Flight Logs 2021.xlsx",
      "source_sheet": "242ML CJ"
    },
    {
      "olat": 39.57012,
      "olng": -104.84929,
      "dlat": 36.04973,
      "dlng": -79.47301,
      "meta": {
        "o": "APA",
        "d": "BUY"
      },
      "tailNum": "",
      "date": "2021-10-02 00:00:00",
      "source_file": "Flight Logs 2021.xlsx",
      "source_sheet": "242ML CJ"
    },
    {
      "olat": 36.04973,
      "olng": -79.47301,
      "dlat": 36.10133,
      "dlng": -79.94112,
      "meta": {
        "o": "BUY",
        "d": "GSO"
      },
      "tailNum": "",
      "date": "2021-10-02 00:00:00",
      "source_file": "Flight Logs 2021.xlsx",
      "source_sheet": "242ML CJ"
    },
    {
      "olat": 36.10133,
      "olng": -79.94112,
      "dlat": 37.64833,
      "dlng": -92.65244,
      "meta": {
        "o": "GSO",
        "d": "LBO"
      },
      "tailNum": "",
      "date": "2021-10-03 00:00:00",
      "source_file": "Flight Logs 2021.xlsx",
      "source_sheet": "242ML CJ"
    },
    {
      "olat": 37.64833,
      "olng": -92.65244,
      "dlat": 39.57012,
      "dlng": -104.84929,
      "meta": {
        "o": "LBO",
        "d": "APA"
      },
      "tailNum": "",
      "date": "2021-10-03 00:00:00",
      "source_file": "Flight Logs 2021.xlsx",
      "source_sheet": "242ML CJ"
    },
    {
      "olat": 39.57012,
      "olng": -104.84929,
      "dlat": 36.04973,
      "dlng": -79.47301,
      "meta": {
        "o": "APA",
        "d": "BUY"
      },
      "tailNum": "",
      "date": "2021-10-04 00:00:00",
      "source_file": "Flight Logs 2021.xlsx",
      "source_sheet": "242ML CJ"
    },
    {
      "olat": 36.04973,
      "olng": -79.47301,
      "dlat": 37.64833,
      "dlng": -92.65244,
      "meta": {
        "o": "BUY",
        "d": "LBO"
      },
      "tailNum": "",
      "date": "2021-10-04 00:00:00",
      "source_file": "Flight Logs 2021.xlsx",
      "source_sheet": "242ML CJ"
    },
    {
      "olat": 37.64833,
      "olng": -92.65244,
      "dlat": 39.57012,
      "dlng": -104.84929,
      "meta": {
        "o": "LBO",
        "d": "APA"
      },
      "tailNum": "",
      "date": "2021-10-04 00:00:00",
      "source_file": "Flight Logs 2021.xlsx",
      "source_sheet": "242ML CJ"
    },
    {
      "olat": 39.57012,
      "olng": -104.84929,
      "dlat": 37.64833,
      "dlng": -92.65244,
      "meta": {
        "o": "APA",
        "d": "LBO"
      },
      "tailNum": "",
      "date": "2021-10-05 00:00:00",
      "source_file": "Flight Logs 2021.xlsx",
      "source_sheet": "242ML CJ"
    },
    {
      "olat": 37.64833,
      "olng": -92.65244,
      "dlat": 36.04973,
      "dlng": -79.47301,
      "meta": {
        "o": "LBO",
        "d": "BUY"
      },
      "tailNum": "",
      "date": "2021-10-05 00:00:00",
      "source_file": "Flight Logs 2021.xlsx",
      "source_sheet": "242ML CJ"
    },
    {
      "olat": 36.04973,
      "olng": -79.47301,
      "dlat": 39.57012,
      "dlng": -104.84929,
      "meta": {
        "o": "BUY",
        "d": "APA"
      },
      "tailNum": "",
      "date": "2021-10-05 00:00:00",
      "source_file": "Flight Logs 2021.xlsx",
      "source_sheet": "242ML CJ"
    },
    {
      "olat": 39.57012,
      "olng": -104.84929,
      "dlat": 37.64833,
      "dlng": -92.65244,
      "meta": {
        "o": "APA",
        "d": "LBO"
      },
      "tailNum": "",
      "date": "2021-10-06 00:00:00",
      "source_file": "Flight Logs 2021.xlsx",
      "source_sheet": "242ML CJ"
    },
    {
      "olat": 37.64833,
      "olng": -92.65244,
      "dlat": 36.04973,
      "dlng": -79.47301,
      "meta": {
        "o": "LBO",
        "d": "BUY"
      },
      "tailNum": "",
      "date": "2021-10-06 00:00:00",
      "source_file": "Flight Logs 2021.xlsx",
      "source_sheet": "242ML CJ"
    },
    {
      "olat": 36.04973,
      "olng": -79.47301,
      "dlat": 38.79061,
      "dlng": -97.65222,
      "meta": {
        "o": "BUY",
        "d": "SLN"
      },
      "tailNum": "",
      "date": "2021-10-06 00:00:00",
      "source_file": "Flight Logs 2021.xlsx",
      "source_sheet": "242ML CJ"
    },
    {
      "olat": 38.79061,
      "olng": -97.65222,
      "dlat": 39.57012,
      "dlng": -104.84929,
      "meta": {
        "o": "SLN",
        "d": "APA"
      },
      "tailNum": "",
      "date": "2021-10-06 00:00:00",
      "source_file": "Flight Logs 2021.xlsx",
      "source_sheet": "242ML CJ"
    },
    {
      "olat": 39.57012,
      "olng": -104.84929,
      "dlat": 38.79061,
      "dlng": -97.65222,
      "meta": {
        "o": "APA",
        "d": "SLN"
      },
      "tailNum": "",
      "date": "2021-10-07 00:00:00",
      "source_file": "Flight Logs 2021.xlsx",
      "source_sheet": "242ML CJ"
    },
    {
      "olat": 38.79061,
      "olng": -97.65222,
      "dlat": 36.04973,
      "dlng": -79.47301,
      "meta": {
        "o": "SLN",
        "d": "BUY"
      },
      "tailNum": "",
      "date": "2021-10-07 00:00:00",
      "source_file": "Flight Logs 2021.xlsx",
      "source_sheet": "242ML CJ"
    },
    {
      "olat": 36.04973,
      "olng": -79.47301,
      "dlat": 37.64833,
      "dlng": -92.65244,
      "meta": {
        "o": "BUY",
        "d": "LBO"
      },
      "tailNum": "",
      "date": "2021-10-07 00:00:00",
      "source_file": "Flight Logs 2021.xlsx",
      "source_sheet": "242ML CJ"
    },
    {
      "olat": 37.64833,
      "olng": -92.65244,
      "dlat": 39.57012,
      "dlng": -104.84929,
      "meta": {
        "o": "LBO",
        "d": "APA"
      },
      "tailNum": "",
      "date": "2021-10-07 00:00:00",
      "source_file": "Flight Logs 2021.xlsx",
      "source_sheet": "242ML CJ"
    },
    {
      "olat": 39.57012,
      "olng": -104.84929,
      "dlat": 36.04973,
      "dlng": -79.47301,
      "meta": {
        "o": "APA",
        "d": "BUY"
      },
      "tailNum": "",
      "date": "2021-10-08 00:00:00",
      "source_file": "Flight Logs 2021.xlsx",
      "source_sheet": "242ML CJ"
    },
    {
      "olat": 36.04973,
      "olng": -79.47301,
      "dlat": 37.64833,
      "dlng": -92.65244,
      "meta": {
        "o": "BUY",
        "d": "LBO"
      },
      "tailNum": "",
      "date": "2021-10-08 00:00:00",
      "source_file": "Flight Logs 2021.xlsx",
      "source_sheet": "242ML CJ"
    },
    {
      "olat": 37.64833,
      "olng": -92.65244,
      "dlat": 39.57012,
      "dlng": -104.84929,
      "meta": {
        "o": "LBO",
        "d": "APA"
      },
      "tailNum": "",
      "date": "2021-10-08 00:00:00",
      "source_file": "Flight Logs 2021.xlsx",
      "source_sheet": "242ML CJ"
    },
    {
      "olat": 39.57012,
      "olng": -104.84929,
      "dlat": 36.04973,
      "dlng": -79.47301,
      "meta": {
        "o": "APA",
        "d": "BUY"
      },
      "tailNum": "",
      "date": "2021-10-09 00:00:00",
      "source_file": "Flight Logs 2021.xlsx",
      "source_sheet": "242ML CJ"
    },
    {
      "olat": 36.04973,
      "olng": -79.47301,
      "dlat": 37.64833,
      "dlng": -92.65244,
      "meta": {
        "o": "BUY",
        "d": "LBO"
      },
      "tailNum": "",
      "date": "2021-10-09 00:00:00",
      "source_file": "Flight Logs 2021.xlsx",
      "source_sheet": "242ML CJ"
    },
    {
      "olat": 37.64833,
      "olng": -92.65244,
      "dlat": 39.57012,
      "dlng": -104.84929,
      "meta": {
        "o": "LBO",
        "d": "APA"
      },
      "tailNum": "",
      "date": "2021-10-09 00:00:00",
      "source_file": "Flight Logs 2021.xlsx",
      "source_sheet": "242ML CJ"
    },
    {
      "olat": 39.57012,
      "olng": -104.84929,
      "dlat": 36.04973,
      "dlng": -79.47301,
      "meta": {
        "o": "APA",
        "d": "BUY"
      },
      "tailNum": "",
      "date": "2021-10-10 00:00:00",
      "source_file": "Flight Logs 2021.xlsx",
      "source_sheet": "242ML CJ"
    },
    {
      "olat": 36.04973,
      "olng": -79.47301,
      "dlat": 37.64833,
      "dlng": -92.65244,
      "meta": {
        "o": "BUY",
        "d": "LBO"
      },
      "tailNum": "",
      "date": "2021-10-10 00:00:00",
      "source_file": "Flight Logs 2021.xlsx",
      "source_sheet": "242ML CJ"
    },
    {
      "olat": 37.64833,
      "olng": -92.65244,
      "dlat": 39.57012,
      "dlng": -104.84929,
      "meta": {
        "o": "LBO",
        "d": "APA"
      },
      "tailNum": "",
      "date": "2021-10-10 00:00:00",
      "source_file": "Flight Logs 2021.xlsx",
      "source_sheet": "242ML CJ"
    },
    {
      "olat": 39.57012,
      "olng": -104.84929,
      "dlat": 36.04973,
      "dlng": -79.47301,
      "meta": {
        "o": "APA",
        "d": "BUY"
      },
      "tailNum": "",
      "date": "2021-10-10 00:00:00",
      "source_file": "Flight Logs 2021.xlsx",
      "source_sheet": "242ML CJ"
    },
    {
      "olat": 36.04973,
      "olng": -79.47301,
      "dlat": 37.64833,
      "dlng": -92.65244,
      "meta": {
        "o": "BUY",
        "d": "LBO"
      },
      "tailNum": "",
      "date": "2021-10-11 00:00:00",
      "source_file": "Flight Logs 2021.xlsx",
      "source_sheet": "242ML CJ"
    },
    {
      "olat": 37.64833,
      "olng": -92.65244,
      "dlat": 39.57012,
      "dlng": -104.84929,
      "meta": {
        "o": "LBO",
        "d": "APA"
      },
      "tailNum": "",
      "date": "2021-10-11 00:00:00",
      "source_file": "Flight Logs 2021.xlsx",
      "source_sheet": "242ML CJ"
    },
    {
      "olat": 39.57012,
      "olng": -104.84929,
      "dlat": 36.04973,
      "dlng": -79.47301,
      "meta": {
        "o": "APA",
        "d": "BUY"
      },
      "tailNum": "",
      "date": "2021-10-12 00:00:00",
      "source_file": "Flight Logs 2021.xlsx",
      "source_sheet": "242ML CJ"
    },
    {
      "olat": 36.04973,
      "olng": -79.47301,
      "dlat": 38.9,
      "dlng": -77.5,
      "meta": {
        "o": "BUY",
        "d": "IAD"
      },
      "tailNum": "",
      "date": "2021-10-12 00:00:00",
      "source_file": "Flight Logs 2021.xlsx",
      "source_sheet": "242ML CJ"
    },
    {
      "olat": 38.9,
      "olng": -77.5,
      "dlat": 40.3785,
      "dlng": -75.96525,
      "meta": {
        "o": "IAD",
        "d": "RDG"
      },
      "tailNum": "",
      "date": "2021-10-12 00:00:00",
      "source_file": "Flight Logs 2021.xlsx",
      "source_sheet": "242ML CJ"
    },
    {
      "olat": 40.3785,
      "olng": -75.96525,
      "dlat": 38.9,
      "dlng": -77.5,
      "meta": {
        "o": "RDG",
        "d": "IAD"
      },
      "tailNum": "",
      "date": "2021-10-12 00:00:00",
      "source_file": "Flight Logs 2021.xlsx",
      "source_sheet": "242ML CJ"
    },
    {
      "olat": 38.9,
      "olng": -77.5,
      "dlat": 36.04973,
      "dlng": -79.47301,
      "meta": {
        "o": "IAD",
        "d": "BUY"
      },
      "tailNum": "",
      "date": "2021-10-12 00:00:00",
      "source_file": "Flight Logs 2021.xlsx",
      "source_sheet": "242ML CJ"
    },
    {
      "olat": 36.04973,
      "olng": -79.47301,
      "dlat": 37.86822,
      "dlng": -95.38694,
      "meta": {
        "o": "BUY",
        "d": "K88"
      },
      "tailNum": "",
      "date": "2021-10-12 00:00:00",
      "source_file": "Flight Logs 2021.xlsx",
      "source_sheet": "242ML CJ"
    },
    {
      "olat": 37.86822,
      "olng": -95.38694,
      "dlat": 39.57012,
      "dlng": -104.84929,
      "meta": {
        "o": "K88",
        "d": "APA"
      },
      "tailNum": "",
      "date": "2021-10-12 00:00:00",
      "source_file": "Flight Logs 2021.xlsx",
      "source_sheet": "242ML CJ"
    },
    {
      "olat": 39.57012,
      "olng": -104.84929,
      "dlat": 36.04973,
      "dlng": -79.47301,
      "meta": {
        "o": "APA",
        "d": "BUY"
      },
      "tailNum": "",
      "date": "2021-10-12 00:00:00",
      "source_file": "Flight Logs 2021.xlsx",
      "source_sheet": "242ML CJ"
    },
    {
      "olat": 36.04973,
      "olng": -79.47301,
      "dlat": 38.79061,
      "dlng": -97.65222,
      "meta": {
        "o": "BUY",
        "d": "SLN"
      },
      "tailNum": "",
      "date": "2021-10-13 00:00:00",
      "source_file": "Flight Logs 2021.xlsx",
      "source_sheet": "242ML CJ"
    },
    {
      "olat": 38.79061,
      "olng": -97.65222,
      "dlat": 39.57012,
      "dlng": -104.84929,
      "meta": {
        "o": "SLN",
        "d": "APA"
      },
      "tailNum": "",
      "date": "2021-10-13 00:00:00",
      "source_file": "Flight Logs 2021.xlsx",
      "source_sheet": "242ML CJ"
    },
    {
      "olat": 39.57012,
      "olng": -104.84929,
      "dlat": 36.04973,
      "dlng": -79.47301,
      "meta": {
        "o": "APA",
        "d": "BUY"
      },
      "tailNum": "",
      "date": "2021-10-14 00:00:00",
      "source_file": "Flight Logs 2021.xlsx",
      "source_sheet": "242ML CJ"
    },
    {
      "olat": 36.04973,
      "olng": -79.47301,
      "dlat": 38.79061,
      "dlng": -97.65222,
      "meta": {
        "o": "BUY",
        "d": "SLN"
      },
      "tailNum": "",
      "date": "2021-10-14 00:00:00",
      "source_file": "Flight Logs 2021.xlsx",
      "source_sheet": "242ML CJ"
    },
    {
      "olat": 38.79061,
      "olng": -97.65222,
      "dlat": 39.57012,
      "dlng": -104.84929,
      "meta": {
        "o": "SLN",
        "d": "APA"
      },
      "tailNum": "",
      "date": "2021-10-14 00:00:00",
      "source_file": "Flight Logs 2021.xlsx",
      "source_sheet": "242ML CJ"
    },
    {
      "olat": 39.57012,
      "olng": -104.84929,
      "dlat": 36.04973,
      "dlng": -79.47301,
      "meta": {
        "o": "APA",
        "d": "BUY"
      },
      "tailNum": "",
      "date": "2021-10-15 00:00:00",
      "source_file": "Flight Logs 2021.xlsx",
      "source_sheet": "242ML CJ"
    },
    {
      "olat": 36.04973,
      "olng": -79.47301,
      "dlat": 37.64833,
      "dlng": -92.65244,
      "meta": {
        "o": "BUY",
        "d": "LBO"
      },
      "tailNum": "",
      "date": "2021-10-15 00:00:00",
      "source_file": "Flight Logs 2021.xlsx",
      "source_sheet": "242ML CJ"
    },
    {
      "olat": 37.64833,
      "olng": -92.65244,
      "dlat": 39.57012,
      "dlng": -104.84929,
      "meta": {
        "o": "LBO",
        "d": "APA"
      },
      "tailNum": "",
      "date": "2021-10-15 00:00:00",
      "source_file": "Flight Logs 2021.xlsx",
      "source_sheet": "242ML CJ"
    },
    {
      "olat": 39.57012,
      "olng": -104.84929,
      "dlat": 36.10133,
      "dlng": -79.94112,
      "meta": {
        "o": "APA",
        "d": "GSO"
      },
      "tailNum": "",
      "date": "2021-10-16 00:00:00",
      "source_file": "Flight Logs 2021.xlsx",
      "source_sheet": "242ML CJ"
    },
    {
      "olat": 36.10133,
      "olng": -79.94112,
      "dlat": 37.64833,
      "dlng": -92.65244,
      "meta": {
        "o": "GSO",
        "d": "LBO"
      },
      "tailNum": "",
      "date": "2021-10-17 00:00:00",
      "source_file": "Flight Logs 2021.xlsx",
      "source_sheet": "242ML CJ"
    },
    {
      "olat": 37.64833,
      "olng": -92.65244,
      "dlat": 39.57012,
      "dlng": -104.84929,
      "meta": {
        "o": "LBO",
        "d": "APA"
      },
      "tailNum": "",
      "date": "2021-10-17 00:00:00",
      "source_file": "Flight Logs 2021.xlsx",
      "source_sheet": "242ML CJ"
    },
    {
      "olat": 39.57012,
      "olng": -104.84929,
      "dlat": 36.04973,
      "dlng": -79.47301,
      "meta": {
        "o": "APA",
        "d": "BUY"
      },
      "tailNum": "",
      "date": "2021-10-18 00:00:00",
      "source_file": "Flight Logs 2021.xlsx",
      "source_sheet": "242ML CJ"
    },
    {
      "olat": 36.04973,
      "olng": -79.47301,
      "dlat": 37.64833,
      "dlng": -92.65244,
      "meta": {
        "o": "BUY",
        "d": "LBO"
      },
      "tailNum": "",
      "date": "2021-10-18 00:00:00",
      "source_file": "Flight Logs 2021.xlsx",
      "source_sheet": "242ML CJ"
    },
    {
      "olat": 37.64833,
      "olng": -92.65244,
      "dlat": 39.57012,
      "dlng": -104.84929,
      "meta": {
        "o": "LBO",
        "d": "APA"
      },
      "tailNum": "",
      "date": "2021-10-18 00:00:00",
      "source_file": "Flight Logs 2021.xlsx",
      "source_sheet": "242ML CJ"
    },
    {
      "olat": 39.57012,
      "olng": -104.84929,
      "dlat": 36.04973,
      "dlng": -79.47301,
      "meta": {
        "o": "APA",
        "d": "BUY"
      },
      "tailNum": "",
      "date": "2021-10-19 00:00:00",
      "source_file": "Flight Logs 2021.xlsx",
      "source_sheet": "242ML CJ"
    },
    {
      "olat": 36.04973,
      "olng": -79.47301,
      "dlat": 37.64833,
      "dlng": -92.65244,
      "meta": {
        "o": "BUY",
        "d": "LBO"
      },
      "tailNum": "",
      "date": "2021-10-19 00:00:00",
      "source_file": "Flight Logs 2021.xlsx",
      "source_sheet": "242ML CJ"
    },
    {
      "olat": 37.64833,
      "olng": -92.65244,
      "dlat": 39.57012,
      "dlng": -104.84929,
      "meta": {
        "o": "LBO",
        "d": "APA"
      },
      "tailNum": "",
      "date": "2021-10-19 00:00:00",
      "source_file": "Flight Logs 2021.xlsx",
      "source_sheet": "242ML CJ"
    },
    {
      "olat": 39.57012,
      "olng": -104.84929,
      "dlat": 36.04973,
      "dlng": -79.47301,
      "meta": {
        "o": "APA",
        "d": "BUY"
      },
      "tailNum": "",
      "date": "2021-10-20 00:00:00",
      "source_file": "Flight Logs 2021.xlsx",
      "source_sheet": "242ML CJ"
    },
    {
      "olat": 36.04973,
      "olng": -79.47301,
      "dlat": 24.72619,
      "dlng": -81.05136,
      "meta": {
        "o": "BUY",
        "d": "MTH"
      },
      "tailNum": "",
      "date": "2021-10-20 00:00:00",
      "source_file": "Flight Logs 2021.xlsx",
      "source_sheet": "242ML CJ"
    },
    {
      "olat": 24.72619,
      "olng": -81.05136,
      "dlat": 36.04973,
      "dlng": -79.47301,
      "meta": {
        "o": "MTH",
        "d": "BUY"
      },
      "tailNum": "",
      "date": "2021-10-20 00:00:00",
      "source_file": "Flight Logs 2021.xlsx",
      "source_sheet": "242ML CJ"
    },
    {
      "olat": 36.04973,
      "olng": -79.47301,
      "dlat": 37.64833,
      "dlng": -92.65244,
      "meta": {
        "o": "BUY",
        "d": "LBO"
      },
      "tailNum": "",
      "date": "2021-10-20 00:00:00",
      "source_file": "Flight Logs 2021.xlsx",
      "source_sheet": "242ML CJ"
    },
    {
      "olat": 37.64833,
      "olng": -92.65244,
      "dlat": 39.57012,
      "dlng": -104.84929,
      "meta": {
        "o": "LBO",
        "d": "APA"
      },
      "tailNum": "",
      "date": "2021-10-20 00:00:00",
      "source_file": "Flight Logs 2021.xlsx",
      "source_sheet": "242ML CJ"
    },
    {
      "olat": 39.57012,
      "olng": -104.84929,
      "dlat": 36.04973,
      "dlng": -79.47301,
      "meta": {
        "o": "APA",
        "d": "BUY"
      },
      "tailNum": "",
      "date": "2021-10-21 00:00:00",
      "source_file": "Flight Logs 2021.xlsx",
      "source_sheet": "242ML CJ"
    },
    {
      "olat": 36.04973,
      "olng": -79.47301,
      "dlat": 37.64833,
      "dlng": -92.65244,
      "meta": {
        "o": "BUY",
        "d": "LBO"
      },
      "tailNum": "",
      "date": "2021-10-21 00:00:00",
      "source_file": "Flight Logs 2021.xlsx",
      "source_sheet": "242ML CJ"
    },
    {
      "olat": 37.64833,
      "olng": -92.65244,
      "dlat": 39.57012,
      "dlng": -104.84929,
      "meta": {
        "o": "LBO",
        "d": "APA"
      },
      "tailNum": "",
      "date": "2021-10-21 00:00:00",
      "source_file": "Flight Logs 2021.xlsx",
      "source_sheet": "242ML CJ"
    },
    {
      "olat": 39.57012,
      "olng": -104.84929,
      "dlat": 36.10133,
      "dlng": -79.94112,
      "meta": {
        "o": "APA",
        "d": "GSO"
      },
      "tailNum": "",
      "date": "2021-10-22 00:00:00",
      "source_file": "Flight Logs 2021.xlsx",
      "source_sheet": "242ML CJ"
    },
    {
      "olat": 36.10133,
      "olng": -79.94112,
      "dlat": 24.72619,
      "dlng": -81.05136,
      "meta": {
        "o": "GSO",
        "d": "MTH"
      },
      "tailNum": "",
      "date": "2021-10-24 00:00:00",
      "source_file": "Flight Logs 2021.xlsx",
      "source_sheet": "242ML CJ"
    },
    {
      "olat": 24.72619,
      "olng": -81.05136,
      "dlat": 36.04973,
      "dlng": -79.47301,
      "meta": {
        "o": "MTH",
        "d": "BUY"
      },
      "tailNum": "",
      "date": "2021-10-24 00:00:00",
      "source_file": "Flight Logs 2021.xlsx",
      "source_sheet": "242ML CJ"
    },
    {
      "olat": 36.04973,
      "olng": -79.47301,
      "dlat": 37.64833,
      "dlng": -92.65244,
      "meta": {
        "o": "BUY",
        "d": "LBO"
      },
      "tailNum": "",
      "date": "2021-10-24 00:00:00",
      "source_file": "Flight Logs 2021.xlsx",
      "source_sheet": "242ML CJ"
    },
    {
      "olat": 37.64833,
      "olng": -92.65244,
      "dlat": 39.57012,
      "dlng": -104.84929,
      "meta": {
        "o": "LBO",
        "d": "APA"
      },
      "tailNum": "",
      "date": "2021-10-24 00:00:00",
      "source_file": "Flight Logs 2021.xlsx",
      "source_sheet": "242ML CJ"
    },
    {
      "olat": 39.57012,
      "olng": -104.84929,
      "dlat": 36.04973,
      "dlng": -79.47301,
      "meta": {
        "o": "APA",
        "d": "BUY"
      },
      "tailNum": "",
      "date": "2021-10-25 00:00:00",
      "source_file": "Flight Logs 2021.xlsx",
      "source_sheet": "242ML CJ"
    },
    {
      "olat": 36.04973,
      "olng": -79.47301,
      "dlat": 32.89864,
      "dlng": -80.04053,
      "meta": {
        "o": "BUY",
        "d": "CHS"
      },
      "tailNum": "",
      "date": "2021-10-25 00:00:00",
      "source_file": "Flight Logs 2021.xlsx",
      "source_sheet": "242ML CJ"
    },
    {
      "olat": 32.89864,
      "olng": -80.04053,
      "dlat": 26.68316,
      "dlng": -80.09559,
      "meta": {
        "o": "CHS",
        "d": "PBI"
      },
      "tailNum": "",
      "date": "2021-10-25 00:00:00",
      "source_file": "Flight Logs 2021.xlsx",
      "source_sheet": "242ML CJ"
    },
    {
      "olat": 26.68316,
      "olng": -80.09559,
      "dlat": 36.04973,
      "dlng": -79.47301,
      "meta": {
        "o": "PBI",
        "d": "BUY"
      },
      "tailNum": "",
      "date": "2021-10-25 00:00:00",
      "source_file": "Flight Logs 2021.xlsx",
      "source_sheet": "242ML CJ"
    },
    {
      "olat": 36.04973,
      "olng": -79.47301,
      "dlat": 37.64833,
      "dlng": -92.65244,
      "meta": {
        "o": "BUY",
        "d": "LBO"
      },
      "tailNum": "",
      "date": "2021-10-25 00:00:00",
      "source_file": "Flight Logs 2021.xlsx",
      "source_sheet": "242ML CJ"
    },
    {
      "olat": 37.64833,
      "olng": -92.65244,
      "dlat": 39.57012,
      "dlng": -104.84929,
      "meta": {
        "o": "LBO",
        "d": "APA"
      },
      "tailNum": "",
      "date": "2021-10-25 00:00:00",
      "source_file": "Flight Logs 2021.xlsx",
      "source_sheet": "242ML CJ"
    },
    {
      "olat": 39.57012,
      "olng": -104.84929,
      "dlat": 36.04973,
      "dlng": -79.47301,
      "meta": {
        "o": "APA",
        "d": "BUY"
      },
      "tailNum": "",
      "date": "2021-10-26 00:00:00",
      "source_file": "Flight Logs 2021.xlsx",
      "source_sheet": "242ML CJ"
    },
    {
      "olat": 36.04973,
      "olng": -79.47301,
      "dlat": 35.87764,
      "dlng": -78.78747,
      "meta": {
        "o": "BUY",
        "d": "RDU"
      },
      "tailNum": "",
      "date": "2021-10-26 00:00:00",
      "source_file": "Flight Logs 2021.xlsx",
      "source_sheet": "242ML CJ"
    },
    {
      "olat": 35.87764,
      "olng": -78.78747,
      "dlat": 39.87208,
      "dlng": -75.24066,
      "meta": {
        "o": "RDU",
        "d": "PHL"
      },
      "tailNum": "",
      "date": "2021-10-26 00:00:00",
      "source_file": "Flight Logs 2021.xlsx",
      "source_sheet": "242ML CJ"
    },
    {
      "olat": 39.87208,
      "olng": -75.24066,
      "dlat": 36.04973,
      "dlng": -79.47301,
      "meta": {
        "o": "PHL",
        "d": "BUY"
      },
      "tailNum": "",
      "date": "2021-10-26 00:00:00",
      "source_file": "Flight Logs 2021.xlsx",
      "source_sheet": "242ML CJ"
    },
    {
      "olat": 36.04973,
      "olng": -79.47301,
      "dlat": 34.27114,
      "dlng": -77.90289,
      "meta": {
        "o": "BUY",
        "d": "ILM"
      },
      "tailNum": "",
      "date": "2021-10-26 00:00:00",
      "source_file": "Flight Logs 2021.xlsx",
      "source_sheet": "242ML CJ"
    },
    {
      "olat": 34.27114,
      "olng": -77.90289,
      "dlat": 30.90147,
      "dlng": -83.88144,
      "meta": {
        "o": "ILM",
        "d": "TVI"
      },
      "tailNum": "",
      "date": "2021-10-26 00:00:00",
      "source_file": "Flight Logs 2021.xlsx",
      "source_sheet": "242ML CJ"
    },
    {
      "olat": 30.90147,
      "olng": -83.88144,
      "dlat": 36.73195,
      "dlng": -97.09978,
      "meta": {
        "o": "TVI",
        "d": "PNC"
      },
      "tailNum": "",
      "date": "2021-10-26 00:00:00",
      "source_file": "Flight Logs 2021.xlsx",
      "source_sheet": "242ML CJ"
    },
    {
      "olat": 36.73195,
      "olng": -97.09978,
      "dlat": 39.57012,
      "dlng": -104.84929,
      "meta": {
        "o": "PNC",
        "d": "APA"
      },
      "tailNum": "",
      "date": "2021-10-26 00:00:00",
      "source_file": "Flight Logs 2021.xlsx",
      "source_sheet": "242ML CJ"
    },
    {
      "olat": 39.57012,
      "olng": -104.84929,
      "dlat": 36.04973,
      "dlng": -79.47301,
      "meta": {
        "o": "APA",
        "d": "BUY"
      },
      "tailNum": "",
      "date": "2021-10-27 00:00:00",
      "source_file": "Flight Logs 2021.xlsx",
      "source_sheet": "242ML CJ"
    },
    {
      "olat": 36.04973,
      "olng": -79.47301,
      "dlat": 36.96453,
      "dlng": -86.41967,
      "meta": {
        "o": "BUY",
        "d": "BWG"
      },
      "tailNum": "",
      "date": "2021-10-27 00:00:00",
      "source_file": "Flight Logs 2021.xlsx",
      "source_sheet": "242ML CJ"
    },
    {
      "olat": 36.96453,
      "olng": -86.41967,
      "dlat": 39.57012,
      "dlng": -104.84929,
      "meta": {
        "o": "BWG",
        "d": "APA"
      },
      "tailNum": "",
      "date": "2021-10-27 00:00:00",
      "source_file": "Flight Logs 2021.xlsx",
      "source_sheet": "242ML CJ"
    },
    {
      "olat": 39.57012,
      "olng": -104.84929,
      "dlat": 36.04973,
      "dlng": -79.47301,
      "meta": {
        "o": "APA",
        "d": "BUY"
      },
      "tailNum": "",
      "date": "2021-10-28 00:00:00",
      "source_file": "Flight Logs 2021.xlsx",
      "source_sheet": "242ML CJ"
    },
    {
      "olat": 36.04973,
      "olng": -79.47301,
      "dlat": 35.87764,
      "dlng": -78.78747,
      "meta": {
        "o": "BUY",
        "d": "RDU"
      },
      "tailNum": "",
      "date": "2021-10-28 00:00:00",
      "source_file": "Flight Logs 2021.xlsx",
      "source_sheet": "242ML CJ"
    },
    {
      "olat": 35.87764,
      "olng": -78.78747,
      "dlat": 36.4,
      "dlng": -86.4,
      "meta": {
        "o": "RDU",
        "d": "XNX"
      },
      "tailNum": "",
      "date": "2021-10-28 00:00:00",
      "source_file": "Flight Logs 2021.xlsx",
      "source_sheet": "242ML CJ"
    },
    {
      "olat": 36.4,
      "olng": -86.4,
      "dlat": 37.50518,
      "dlng": -77.31974,
      "meta": {
        "o": "XNX",
        "d": "RIC"
      },
      "tailNum": "",
      "date": "2021-10-28 00:00:00",
      "source_file": "Flight Logs 2021.xlsx",
      "source_sheet": "242ML CJ"
    },
    {
      "olat": 37.50518,
      "olng": -77.31974,
      "dlat": 36.04973,
      "dlng": -79.47301,
      "meta": {
        "o": "RIC",
        "d": "BUY"
      },
      "tailNum": "",
      "date": "2021-10-28 00:00:00",
      "source_file": "Flight Logs 2021.xlsx",
      "source_sheet": "242ML CJ"
    },
    {
      "olat": 36.04973,
      "olng": -79.47301,
      "dlat": 36.96453,
      "dlng": -86.41967,
      "meta": {
        "o": "BUY",
        "d": "BWG"
      },
      "tailNum": "",
      "date": "2021-10-28 00:00:00",
      "source_file": "Flight Logs 2021.xlsx",
      "source_sheet": "242ML CJ"
    },
    {
      "olat": 36.96453,
      "olng": -86.41967,
      "dlat": 39.57012,
      "dlng": -104.84929,
      "meta": {
        "o": "BWG",
        "d": "APA"
      },
      "tailNum": "",
      "date": "2021-10-28 00:00:00",
      "source_file": "Flight Logs 2021.xlsx",
      "source_sheet": "242ML CJ"
    },
    {
      "olat": 39.57012,
      "olng": -104.84929,
      "dlat": 36.04973,
      "dlng": -79.47301,
      "meta": {
        "o": "APA",
        "d": "BUY"
      },
      "tailNum": "",
      "date": "2021-10-29 00:00:00",
      "source_file": "Flight Logs 2021.xlsx",
      "source_sheet": "242ML CJ"
    },
    {
      "olat": 36.04973,
      "olng": -79.47301,
      "dlat": 37.64833,
      "dlng": -92.65244,
      "meta": {
        "o": "BUY",
        "d": "LBO"
      },
      "tailNum": "",
      "date": "2021-10-29 00:00:00",
      "source_file": "Flight Logs 2021.xlsx",
      "source_sheet": "242ML CJ"
    },
    {
      "olat": 37.64833,
      "olng": -92.65244,
      "dlat": 39.57012,
      "dlng": -104.84929,
      "meta": {
        "o": "LBO",
        "d": "APA"
      },
      "tailNum": "",
      "date": "2021-10-29 00:00:00",
      "source_file": "Flight Logs 2021.xlsx",
      "source_sheet": "242ML CJ"
    },
    {
      "olat": 39.57012,
      "olng": -104.84929,
      "dlat": 36.04973,
      "dlng": -79.47301,
      "meta": {
        "o": "APA",
        "d": "BUY"
      },
      "tailNum": "",
      "date": "2021-10-30 00:00:00",
      "source_file": "Flight Logs 2021.xlsx",
      "source_sheet": "242ML CJ"
    },
    {
      "olat": 36.04973,
      "olng": -79.47301,
      "dlat": 37.86822,
      "dlng": -95.38694,
      "meta": {
        "o": "BUY",
        "d": "K88"
      },
      "tailNum": "",
      "date": "2021-10-30 00:00:00",
      "source_file": "Flight Logs 2021.xlsx",
      "source_sheet": "242ML CJ"
    },
    {
      "olat": 37.86822,
      "olng": -95.38694,
      "dlat": 39.57012,
      "dlng": -104.84929,
      "meta": {
        "o": "K88",
        "d": "APA"
      },
      "tailNum": "",
      "date": "2021-10-30 00:00:00",
      "source_file": "Flight Logs 2021.xlsx",
      "source_sheet": "242ML CJ"
    },
    {
      "olat": 39.57012,
      "olng": -104.84929,
      "dlat": 36.04973,
      "dlng": -79.47301,
      "meta": {
        "o": "APA",
        "d": "BUY"
      },
      "tailNum": "",
      "date": "2021-10-31 00:00:00",
      "source_file": "Flight Logs 2021.xlsx",
      "source_sheet": "242ML CJ"
    },
    {
      "olat": 36.04973,
      "olng": -79.47301,
      "dlat": 37.64833,
      "dlng": -92.65244,
      "meta": {
        "o": "BUY",
        "d": "LBO"
      },
      "tailNum": "",
      "date": "2021-10-31 00:00:00",
      "source_file": "Flight Logs 2021.xlsx",
      "source_sheet": "242ML CJ"
    },
    {
      "olat": 37.64833,
      "olng": -92.65244,
      "dlat": 39.57012,
      "dlng": -104.84929,
      "meta": {
        "o": "LBO",
        "d": "APA"
      },
      "tailNum": "",
      "date": "2021-10-31 00:00:00",
      "source_file": "Flight Logs 2021.xlsx",
      "source_sheet": "242ML CJ"
    },
    {
      "olat": 36.10133,
      "olng": -79.94112,
      "dlat": 36.04973,
      "dlng": -79.47301,
      "meta": {
        "o": "GSO",
        "d": "BUY"
      },
      "tailNum": "",
      "date": "2021-10-07 00:00:00",
      "source_file": "Flight Logs 2021.xlsx",
      "source_sheet": "90KM CJ3"
    }
  ]
}